sos/__init__.py
sos/__main__.py
sos/_version.py
sos/actions.py
sos/actions_bash.py
sos/actions_javascript.py
sos/actions_julia.py
sos/actions_matlab.py
sos/actions_python.py
sos/actions_r.py
sos/actions_ruby.py
sos/controller.py
sos/converter.py
sos/dag.py
sos/eval.py
sos/executor_utils.py
sos/functions.py
sos/hosts.py
sos/install.py
sos/messages.py
sos/monitor.py
sos/parser.py
sos/pattern.py
sos/preview.py
sos/remote.py
sos/runtime.py
sos/section_analyzer.py
sos/signatures.py
sos/step_executor.py
sos/substep_executor.py
sos/syntax.py
sos/targets.py
sos/targets_python.py
sos/targets_r.py
sos/task_engines.py
sos/task_executor.py
sos/tasks.py
sos/utils.py
sos/visualize.py
sos/workers.py
sos/workflow_engines.py
sos/workflow_executor.py
sos/workflow_report.py
sos/docker/__init__.py
sos/docker/actions.py
sos/docker/client.py
sos/singularity/__init__.py
sos/singularity/actions.py
sos/singularity/client.py
sos/templates/sos_script.tpl
sos/templates/workflow_report.tpl
sos/templates/parts/hover_doc.tpl
sos/templates/parts/sos-mode.js
sos/templates/parts/sos_report.css
sos/vim/sos-detect.vim
sos/vim/sos.vim
sos-0.25.1.dist-info/LICENSE
sos-0.25.1.dist-info/METADATA
sos-0.25.1.dist-info/WHEEL
sos-0.25.1.dist-info/entry_points.txt
sos-0.25.1.dist-info/top_level.txt
sos-0.25.1.dist-info/RECORD
