Metadata-Version: 2.1
Name: sos
Version: 0.25.1
Summary: Script of Scripts (SoS): an interactive, cross-platform, and cross-language workflow system for reproducible data analysis
Home-page: https://github.com/vatlab/SoS
Author: Bo Peng
Author-email: Bo.Peng@bcm.edu
Maintainer: Bo Peng
Maintainer-email: Bo.Peng@bcm.edu
License: 3-clause BSD
Classifier: Development Status :: 4 - Beta
Classifier: Environment :: Console
Classifier: License :: OSI Approved :: BSD License
Classifier: Natural Language :: English
Classifier: Operating System :: POSIX :: Linux
Classifier: Operating System :: MacOS :: MacOS X
Classifier: Operating System :: Microsoft :: Windows
Classifier: Intended Audience :: Information Technology
Classifier: Intended Audience :: Science/Research
Classifier: Programming Language :: Python :: 3 :: Only
Classifier: Programming Language :: Python :: 3.6
Classifier: Programming Language :: Python :: 3.7
Classifier: Programming Language :: Python :: 3.8
Classifier: Programming Language :: Python :: Implementation :: CPython
Classifier: Programming Language :: Python :: Implementation :: PyPy
Requires-Python: >=3.6
License-File: LICENSE
Requires-Dist: psutil
Requires-Dist: tqdm
Requires-Dist: fasteners
Requires-Dist: pyyaml
Requires-Dist: pygments
Requires-Dist: networkx!=2.8.3
Requires-Dist: pydot
Requires-Dist: pydotplus
Requires-Dist: pexpect
Requires-Dist: ptyprocess
Requires-Dist: jinja2
Requires-Dist: nbformat
Requires-Dist: pyzmq
Requires-Dist: colorama; sys_platform == "win32"
Requires-Dist: xxhash; sys_platform != "win32"
Provides-Extra: dot
Requires-Dist: graphviz; extra == "dot"
Requires-Dist: pillow; extra == "dot"
